blinkistconfig/__init__.py
blinkistconfig/config.py
blinkistconfig/adapters/__init__.py
blinkistconfig/adapters/env_adapter.py
blinkistconfig/adapters/factory.py
blinkistconfig/adapters/ssm_adapter.py
blinkistconfig/errors/__init__.py
blinkistconfig/errors/adapter_not_found_error.py
blinkistconfig/errors/base.py
blinkistconfig/errors/value_missing_error.py
blinkistconfig-0.0.4.dist-info/METADATA
blinkistconfig-0.0.4.dist-info/RECORD
blinkistconfig-0.0.4.dist-info/WHEEL
blinkistconfig-0.0.4.dist-info/top_level.txt
