Metadata-Version: 2.1
Name: blinkistconfig
Version: 0.0.4
Summary: Adapter based configuration handler (supports ENV and AWS SSM).
Home-page: https://github.com/blinkist/blinkist-config-python
Author: Peter Shoukry
Author-email: peter@blinkist.com
License: UNKNOWN
Platform: UNKNOWN
Classifier: Programming Language :: Python :: 3
Classifier: License :: OSI Approved :: MIT License
Classifier: Operating System :: OS Independent
Requires-Dist: boto3
